{
    "custom_res_type": "custom_editor_model", 
    "describe": "test_describe", 
    "has_upload": false, 
    "key": 134229289, 
    "md5": "9cf697c2afe04c9f8625504cee4117d7", 
    "model_id": 134229289, 
    "name": "G58_Background_04", 
    "preview_icon": "UP1ModelPreview/134229289", 
    "preview_item": {
        "key": 134229289, 
        "path": "UP1ModelPreview/134229289", 
        "size": "100X68"
    }, 
    "res_name": "G58_Background_04.fbx", 
    "res_type": "kkres", 
    "rotate_y": 0.0, 
    "select_effect_scale": 1.0, 
    "size": 1.0, 
    "socket_info": {}, 
    "sub_type": "fbx", 
    "uid": 134229289, 
    "url": "https://kk3.nosdn.127.net/editor/png/72ca5213b10f5f167755df5b6b02b0c1.png", 
    "version": 1, 
    "yaw": 0
}