{
    "action": [
        [
            1563912672, 
            "获取三个随机技能，写入【幸存者_升级选择集合】", 
            1475612714, 
            "action_type"
        ], 
        {
            "action_type": "PRINT_MESSAGE_ACTION_TO_DIALOG", 
            "args_list": [
                {
                    "arg_type": 100175, 
                    "args_list": [
                        3
                    ], 
                    "sub_type": 1
                }, 
                {
                    "arg_type": 100003, 
                    "args_list": [
                        {
                            "arg_type": 100003, 
                            "args_list": [
                                "玩家"
                            ], 
                            "sub_type": 1
                        }, 
                        {
                            "arg_type": 100003, 
                            "args_list": [
                                {
                                    "arg_type": 100025, 
                                    "args_list": [], 
                                    "sub_type": "GET_CLIENT_ROLE"
                                }
                            ], 
                            "sub_type": "ANY_VAR_TO_STR"
                        }
                    ], 
                    "op_arg": [
                        {
                            "arg_type": 100003, 
                            "args_list": [
                                "开启暂停"
                            ], 
                            "sub_type": 1
                        }, 
                        null, 
                        null, 
                        null, 
                        null, 
                        null, 
                        null, 
                        null
                    ], 
                    "op_arg_enable": [
                        true, 
                        false, 
                        false, 
                        false, 
                        false, 
                        false, 
                        false, 
                        false
                    ], 
                    "sub_type": "STR_JOIN"
                }
            ], 
            "bp": false, 
            "element_id": 1475612714000001, 
            "enable": true
        }, 
        {
            "action_type": "CALL_TRIGGER_FUNC", 
            "args_list": [
                {
                    "arg_type": 100177, 
                    "args_list": [
                        {
                            "arg_type": 100006, 
                            "args_list": [
                                {
                                    "arg_type": 100011, 
                                    "args_list": [
                                        [
                                            "TABLE", 
                                            "幸存者_玩家数据表"
                                        ]
                                    ], 
                                    "sub_type": "VARIABLE"
                                }, 
                                {
                                    "arg_type": 100002, 
                                    "args_list": [
                                        {
                                            "arg_type": 100025, 
                                            "args_list": [
                                                [
                                                    "PLAYER", 
                                                    "待升级玩家", 
                                                    "local"
                                                ]
                                            ], 
                                            "sub_type": "VARIABLE"
                                        }
                                    ], 
                                    "sub_type": "PLAYER_ID_NUMBER"
                                }, 
                                {
                                    "arg_type": 100003, 
                                    "args_list": [
                                        "单位"
                                    ], 
                                    "sub_type": 1
                                }
                            ], 
                            "sub_type": "GET_UNIT_ENTITY_TABLE_VAR_ND"
                        }
                    ], 
                    "op_arg": [], 
                    "op_arg_enable": [], 
                    "sub_type": "a63829a1845111ee9e8b30d042e90e85"
                }
            ], 
            "bp": false, 
            "call_rt_arg_idxes": [], 
            "element_id": 1475612714000003, 
            "enable": true
        }, 
        {
            "action_type": "IF_THEN_ELSE", 
            "args_list": [
                {
                    "arg_type": 100021, 
                    "args_list": [
                        {
                            "args_list": [
                                {
                                    "arg_type": 100001, 
                                    "args_list": [
                                        {
                                            "arg_type": 100011, 
                                            "args_list": [
                                                {
                                                    "__tuple__": true, 
                                                    "items": [
                                                        "TABLE", 
                                                        "幸存者_玩家数据表"
                                                    ]
                                                }
                                            ], 
                                            "sub_type": "VARIABLE"
                                        }, 
                                        {
                                            "arg_type": 100002, 
                                            "args_list": [
                                                {
                                                    "arg_type": 100025, 
                                                    "args_list": [
                                                        [
                                                            "PLAYER", 
                                                            "待升级玩家", 
                                                            "local"
                                                        ]
                                                    ], 
                                                    "sub_type": "VARIABLE"
                                                }
                                            ], 
                                            "sub_type": "PLAYER_ID_NUMBER"
                                        }, 
                                        {
                                            "arg_type": 100003, 
                                            "args_list": [
                                                "是否自动升级"
                                            ], 
                                            "sub_type": 1
                                        }
                                    ], 
                                    "sub_type": "GET_BOOLEAN_TABLE_VAR_ND"
                                }, 
                                {
                                    "arg_type": 100035, 
                                    "args_list": [
                                        "=="
                                    ], 
                                    "sub_type": 1
                                }, 
                                {
                                    "arg_type": 100001, 
                                    "args_list": [
                                        true
                                    ], 
                                    "sub_type": 1
                                }
                            ], 
                            "condition_type": "BOOL_COMPARE", 
                            "element_id": 1475612714912684, 
                            "enable": true
                        }
                    ], 
                    "sub_type": 1
                }, 
                {
                    "arg_type": 100022, 
                    "args_list": [
                        {
                            "action_type": "CALL_TRIGGER_FUNC", 
                            "args_list": [
                                {
                                    "arg_type": 100177, 
                                    "args_list": [
                                        {
                                            "arg_type": 100002, 
                                            "args_list": [
                                                {
                                                    "arg_type": 100002, 
                                                    "args_list": [
                                                        1
                                                    ], 
                                                    "sub_type": 1
                                                }, 
                                                {
                                                    "arg_type": 100002, 
                                                    "args_list": [
                                                        5
                                                    ], 
                                                    "sub_type": 1
                                                }
                                            ], 
                                            "sub_type": "RANDOM_INT"
                                        }, 
                                        {
                                            "arg_type": 100025, 
                                            "args_list": [
                                                [
                                                    "PLAYER", 
                                                    "待升级玩家", 
                                                    "local"
                                                ]
                                            ], 
                                            "sub_type": "VARIABLE"
                                        }
                                    ], 
                                    "op_arg": [], 
                                    "op_arg_enable": [], 
                                    "sub_type": "a87839de78b111eebdb730d042e90e85"
                                }
                            ], 
                            "bp": false, 
                            "call_rt_arg_idxes": [], 
                            "element_id": 1854984238000002, 
                            "enable": true
                        }
                    ], 
                    "sub_type": 1
                }, 
                {
                    "arg_type": 100022, 
                    "args_list": [
                        {
                            "action_type": "SOFT_PAUSE_GAME", 
                            "args_list": [], 
                            "bp": false, 
                            "element_id": 1475612714000002, 
                            "enable": true
                        }, 
                        {
                            "action_type": "SEND_CUSTOM_EVENT", 
                            "args_list": [
                                {
                                    "arg_type": 100238, 
                                    "args_list": [
                                        1078706893
                                    ], 
                                    "sub_type": 1
                                }, 
                                {
                                    "arg_type": 100025, 
                                    "args_list": [
                                        [
                                            "PLAYER", 
                                            "待升级玩家", 
                                            "local"
                                        ]
                                    ], 
                                    "sub_type": "VARIABLE"
                                }
                            ], 
                            "bp": false, 
                            "element_id": 1475612714000004, 
                            "enable": true
                        }
                    ], 
                    "sub_type": 1
                }
            ], 
            "bp": false, 
            "element_id": 1475612714912675, 
            "enable": true, 
            "fake_op": [
                2
            ]
        }
    ], 
    "call_enabled": true, 
    "condition": [], 
    "enabled": true, 
    "event": [], 
    "func_category": "t_function", 
    "func_comment": "", 
    "func_des": "玩家升级{待升级玩家}", 
    "func_id": "6152d2f078ac11eeb9cf30d042e90e85", 
    "func_name": "幸存者_玩家升级", 
    "func_param_list": [
        {
            "__tuple__": true, 
            "items": [
                "待升级玩家", 
                true
            ]
        }
    ], 
    "group_id": "xf3cIYetEe+qfFcCQ6y3FZ", 
    "is_func": true, 
    "is_official_func": false, 
    "p_trigger_id": null, 
    "trigger_id": 1475612714, 
    "trigger_name": "幸存者_玩家升级", 
    "valid": true, 
    "var_data": [
        {
            "ABILITY_NAME": {
                "当前技能类型": 0
            }, 
            "INTEGER": {
                "data1": 0, 
                "data2": 0, 
                "data3": 0, 
                "i": 0, 
                "表索引集合": 0, 
                "表长": 0
            }, 
            "NEW_TIMER": {}, 
            "PLAYER": {
                "待升级玩家": 0
            }
        }, 
        {
            "data1": 0, 
            "data2": 0, 
            "data3": 0, 
            "i": 0, 
            "当前技能类型": 0, 
            "待升级玩家": 0, 
            "表索引集合": 10, 
            "表长": 0
        }, 
        [
            "i", 
            "当前技能类型", 
            "表索引集合", 
            "表长", 
            "data1", 
            "data2", 
            "data3", 
            "待升级玩家"
        ]
    ]
}