{
    "anims": {}, 
    "box": [
        -2.5000009536743164, 
        -9.999999974752427e-7, 
        -2.5, 
        1.1243059635162354, 
        1.1094030141830444, 
        2.5
    ], 
    "custom": true, 
    "graph": "", 
    "graph_info": {
        "graph": null, 
        "head_bone": "", 
        "root_bone": "", 
        "upper_bone": ""
    }, 
    "meshes": [
        "custom_model/134274524/SM_Scafoldings_T"
    ], 
    "model_id": 134274524, 
    "name": "SM_Scafoldings_T", 
    "physics_meshes": [
        "custom_model/134274524/AutoPhy_Mesh_SM_Scafoldings_T"
    ], 
    "preview_icon": "UP1ModelPreview/134274524", 
    "skeleton": "", 
    "textures": []
}